odisi/__init__.py
odisi/odisi.py
odisi/reader.py
odisi/time_callibration.py
odisi/utils.py
python_odisi-0.7.1.dist-info/METADATA
python_odisi-0.7.1.dist-info/WHEEL
python_odisi-0.7.1.dist-info/licenses/LICENSE
python_odisi-0.7.1.dist-info/RECORD
