Metadata-Version: 2.4
Name: python-odisi
Version: 0.7.1
Summary: Import and post-process data generated by the Luna ODiSI System
Author-email: Cristóbal Tapia Camú <crtapia@gmail.com>
License-Expression: MIT
License-File: LICENSE
Keywords: import,odisi,reader
Requires-Python: >=3.10
Requires-Dist: matplotlib>=3.10.0
Requires-Dist: numpy>=2.0
Requires-Dist: polars>=1.17.1
